{
    "_lookup": ["table_name"],
    "_translate": ["title"],
    "name": "contact_extra",
    "title": "Zusatzinfos Kontakt",
    "extends": "Contact",
    "style": "Inline",
    "collapse_display": "0",
    "is_active": "1",
    "weight": "1000",
    "table_name": "civicrm_value_contact_extra",
    "is_multiple": "0",
    "collapse_adv_display": "1",
    "is_reserved": "0",
    "_fields": [{
            "_lookup": ["column_name"],
            "_translate": ["label"],
            "name": "navision_id",
            "label": "Navision ID",
            "data_type": "String",
            "html_type": "Text",
            "is_required": "0",
            "is_searchable": "1",
            "is_search_range": "0",
            "is_active": "1",
            "is_view": "0",
            "text_length": "128",
            "column_name": "navision_id",
            "in_selector": "0"
        },
        {
            "_lookup": ["column_name"],
            "_translate": ["label"],
            "name": "additional_languages",
            "label": "Weitere Sprachen",
            "data_type": "String",
            "html_type": "Multi-Select",
            "option_group_id": "languages",
            "is_required": "0",
            "is_searchable": "1",
            "is_search_range": "0",
            "is_active": "1",
            "is_view": "0",
            "text_length": "128",
            "column_name": "additional_languages",
            "in_selector": "0"
        }
    ]
}
